sherpa_ncnn/__main__.py
sherpa_ncnn/_info.py
sherpa_ncnn/include/sherpa-ncnn/c-api/c-api.h
sherpa_ncnn/lib/ncnn.dll
sherpa_ncnn/lib/ncnn.lib
sherpa_ncnn/lib/sherpa-ncnn-c-api.dll
sherpa_ncnn/lib/sherpa-ncnn-c-api.lib
sherpa_ncnn_core-2.1.15.data/data/Scripts/ncnn.dll
sherpa_ncnn_core-2.1.15.data/data/Scripts/sherpa-ncnn-c-api.dll
sherpa_ncnn_core-2.1.15.data/data/Scripts/sherpa-ncnn-c-api.lib
sherpa_ncnn_core-2.1.15.dist-info/METADATA
sherpa_ncnn_core-2.1.15.dist-info/WHEEL
sherpa_ncnn_core-2.1.15.dist-info/top_level.txt
sherpa_ncnn_core-2.1.15.dist-info/RECORD
