Metadata-Version: 2.1
Name: sherpa-ncnn-core
Version: 2.1.15
Summary: Core shared libraries for sherpa-ncnn
Home-page: https://github.com/k2-fsa/sherpa-ncnn
Author: The sherpa-ncnn development team
Author-email: dpovey@gmail.com
License: Apache-2.0
Classifier: Programming Language :: Python :: 3
Classifier: Operating System :: Microsoft :: Windows
Classifier: Operating System :: POSIX :: Linux
Classifier: Operating System :: MacOS :: MacOS X
Classifier: Topic :: Scientific/Engineering :: Artificial Intelligence
